{
  "items": [
    {
      "slug": "mid-autumn",
      "title": "Mid-Autumn Festival",
      "subtitle": "中秋節 · SHORT",
      "cover": "videos/mid-autumn.jpg",
      "video": "videos/mid-autumn.mp4",
      "free": true,
      "length": "SHORT",
      "tags": ["中秋節", "短篇"]
    },
    {
      "slug": "houyi",
      "title": "Hou Yi Shoots the Suns",
      "subtitle": "后羿射日 · SHORT",
      "cover": "videos/houyi.jpg",
      "video": "videos/houyi.mp4",
      "free": false,
      "length": "SHORT",
      "tags": ["后羿射日", "短篇"]
    },
    {
      "slug": "lantern",
      "title": "Lantern Festival",
      "subtitle": "元宵節 · SHORT",
      "cover": "videos/lantern.jpg",
      "video": "videos/Lantern.mp4",
      "free": false,
      "length": "SHORT",
      "tags": ["元宵節", "短篇"]
    }
  ]
}
